{
  "meta": {
    "fetched_at": "2026-06-05T21:25:46Z",
    "source": "cbr.ru"
  },
  "key_rate": {
    "current": 14.5,
    "effective_from": "2026-06-05",
    "unit": "%_per_annum"
  },
  "ruonia": {
    "error": "Table not found on RUONIA page"
  },
  "fx_rates": {
    "date": "2026-06-06",
    "GBP": {
      "rate": 98.7789,
      "nominal": 1
    },
    "USD": {
      "rate": 73.4689,
      "nominal": 1
    },
    "EUR": {
      "rate": 85.5582,
      "nominal": 1
    },
    "CNY": {
      "rate": 10.853,
      "nominal": 1
    }
  },
  "inflation": {
    "error": "HTTP 403 from inflation page"
  },
  "m2": {
    "error": "M2 data is JavaScript-rendered on cbr.ru and cannot be scraped statically. Use the CBR website directly or find an alternative data source."
  },
  "gold": {
    "latest": {
      "date": "2026-06-05",
      "rate": 10616.63
    },
    "unit": "RUB_per_gram"
  }
}
