{
  "meta": {
    "fetched_at": "2026-06-17T04:05:14Z",
    "source": "cbr.ru"
  },
  "key_rate": {
    "current": 14.5,
    "effective_from": "2026-06-16",
    "unit": "%_per_annum"
  },
  "ruonia": {
    "latest": {
      "date": "2026-06-15",
      "rate": 13.82
    }
  },
  "fx_rates": {
    "date": "2026-06-17",
    "GBP": {
      "rate": 96.9618,
      "nominal": 1
    },
    "USD": {
      "rate": 72.1388,
      "nominal": 1
    },
    "EUR": {
      "rate": 83.7315,
      "nominal": 1
    },
    "CNY": {
      "rate": 10.6624,
      "nominal": 1
    }
  },
  "inflation": {
    "latest": {
      "period": "2026-05",
      "yoy_pct": 5.31
    },
    "unit": "%_yoy"
  },
  "m2": {
    "error": "M2 data is JavaScript-rendered on cbr.ru and cannot be scraped statically. Use the CBR website directly or find an alternative data source."
  },
  "gold": {
    "latest": {
      "date": "2026-06-17",
      "rate": 10101.08
    },
    "unit": "RUB_per_gram"
  }
}
